CHANGELOG.md
LICENSE.txt
MANIFEST.in
README.md
setup.py
shayhan/__init__.py
shayhan.egg-info/PKG-INFO
shayhan.egg-info/SOURCES.txt
shayhan.egg-info/dependency_links.txt
shayhan.egg-info/top_level.txt