Metadata-Version: 2.1
Name: shayhan
Version: 0.0.1
Summary: This is a libriry of some fuctions
Home-page: UNKNOWN
Author: Shayhan Ameen Chowdhury
Author-email: shayhan.ameen@gmail.com
License: MIT
Keywords: print
Platform: UNKNOWN
Classifier: Development Status :: 5 - Production/Stable
Classifier: Intended Audience :: Education
Classifier: Operating System :: Microsoft :: Windows :: Windows 10
Classifier: License :: OSI Approved :: MIT License
Classifier: Programming Language :: Python :: 3
License-File: LICENSE.txt
